pega/__about__.py
pega/__init__.py
pega/cli.py
pega-0.3.0.dist-info/METADATA
pega-0.3.0.dist-info/WHEEL
pega-0.3.0.dist-info/entry_points.txt
pega-0.3.0.dist-info/licenses/LICENSE.txt
pega-0.3.0.dist-info/RECORD
