Metadata-Version: 2.1
Name: pega
Version: 0.3.0
Summary: A command line tool for pasting images on top of other images.
Project-URL: Documentation, https://github.com/yaph/pega#readme
Project-URL: Issues, https://github.com/yaph/pega/issues
Project-URL: Source, https://github.com/yaph/pega
Author-email: Ramiro Gómez <code@ramiro.org>
License-File: LICENSE.txt
Keywords: image-processing
Classifier: Development Status :: 4 - Beta
Classifier: Programming Language :: Python
Classifier: Programming Language :: Python :: 3.7
Classifier: Programming Language :: Python :: 3.8
Classifier: Programming Language :: Python :: 3.9
Classifier: Programming Language :: Python :: 3.10
Classifier: Programming Language :: Python :: 3.11
Classifier: Programming Language :: Python :: Implementation :: CPython
Classifier: Programming Language :: Python :: Implementation :: PyPy
Requires-Python: >=3.7
Requires-Dist: pillow
